{
  "analytics": {
    "LevelUpFitnessAPNS": {
      "providerPlugin": "awscloudformation",
      "service": "Pinpoint"
    }
  },
  "api": {
    "LevelUpFitnessCustomProgramRequestAPI": {
      "dependsOn": [
        {
          "attributes": [
            "Name",
            "Arn"
          ],
          "category": "function",
          "resourceName": "LevelUpFitnessCustomProgramRequestLambda"
        }
      ],
      "providerPlugin": "awscloudformation",
      "service": "API Gateway"
    },
    "LevelUpFitnessDynamoAccessAPI": {
      "dependsOn": [
        {
          "attributes": [
            "Name",
            "Arn"
          ],
          "category": "function",
          "resourceName": "LevelUpFitnessDynamoAccessLambda"
        }
      ],
      "providerPlugin": "awscloudformation",
      "service": "API Gateway"
    },
    "LevelUpFitnessS3AccessAPI": {
      "dependsOn": [
        {
          "attributes": [
            "Name",
            "Arn"
          ],
          "category": "function",
          "resourceName": "LevelUpFitnessS3AccessLambda"
        }
      ],
      "providerPlugin": "awscloudformation",
      "service": "API Gateway"
    }
  },
  "auth": {
    "levelupfitnessapp07d30c36": {
      "customAuth": false,
      "dependsOn": [],
      "frontendAuthConfig": {
        "mfaConfiguration": "OFF",
        "mfaTypes": [
          "SMS"
        ],
        "passwordProtectionSettings": {
          "passwordPolicyCharacters": [],
          "passwordPolicyMinLength": 8
        },
        "signupAttributes": [
          "EMAIL"
        ],
        "socialProviders": [],
        "usernameAttributes": [
          "EMAIL"
        ],
        "verificationMechanisms": [
          "EMAIL"
        ]
      },
      "providerPlugin": "awscloudformation",
      "service": "Cognito"
    }
  },
  "function": {
    "LevelUpFitnessChallengeExpirationCheckLambda": {
      "build": true,
      "providerPlugin": "awscloudformation",
      "service": "Lambda"
    },
    "LevelUpFitnessChallengeNotificationsLambda": {
      "build": true,
      "dependsOn": [
        {
          "attributes": [
            "Name",
            "Arn",
            "StreamArn"
          ],
          "category": "storage",
          "resourceName": "LevelUpFitnessUserChallengesDB"
        }
      ],
      "providerPlugin": "awscloudformation",
      "service": "Lambda"
    },
    "LevelUpFitnessCustomProgramRequestLambda": {
      "build": true,
      "dependsOn": [
        {
          "attributes": [
            "Name",
            "Arn",
            "StreamArn"
          ],
          "category": "storage",
          "resourceName": "LevelUpFitnessCustomProgramRequestDB"
        }
      ],
      "providerPlugin": "awscloudformation",
      "service": "Lambda"
    },
    "LevelUpFitnessDynamoAccessLambda": {
      "build": true,
      "providerPlugin": "awscloudformation",
      "service": "Lambda"
    },
    "LevelUpFitnessS3AccessLambda": {
      "build": true,
      "dependsOn": [
        {
          "attributes": [
            "BucketName"
          ],
          "category": "storage",
          "resourceName": "LevelUpFitnessStorage"
        }
      ],
      "providerPlugin": "awscloudformation",
      "service": "Lambda"
    }
  },
  "notifications": {
    "LevelUpFitnessAPNS": {
      "channels": [
        "APNS"
      ],
      "service": "Pinpoint"
    }
  },
  "parameters": {
    "AMPLIFY_analytics_Pinpoint_Id": {
      "usedBy": [
        {
          "category": "analytics",
          "resourceName": "Pinpoint"
        }
      ]
    },
    "AMPLIFY_analytics_Pinpoint_Name": {
      "usedBy": [
        {
          "category": "analytics",
          "resourceName": "Pinpoint"
        }
      ]
    },
    "AMPLIFY_analytics_Pinpoint_Region": {
      "usedBy": [
        {
          "category": "analytics",
          "resourceName": "Pinpoint"
        }
      ]
    },
    "AMPLIFY_function_LevelUpFitnessChallengeExpirationCheckLambda_deploymentBucketName": {
      "usedBy": [
        {
          "category": "function",
          "resourceName": "LevelUpFitnessChallengeExpirationCheckLambda"
        }
      ]
    },
    "AMPLIFY_function_LevelUpFitnessChallengeExpirationCheckLambda_s3Key": {
      "usedBy": [
        {
          "category": "function",
          "resourceName": "LevelUpFitnessChallengeExpirationCheckLambda"
        }
      ]
    },
    "AMPLIFY_function_LevelUpFitnessChallengeNotificationsLambda_deploymentBucketName": {
      "usedBy": [
        {
          "category": "function",
          "resourceName": "LevelUpFitnessChallengeNotificationsLambda"
        }
      ]
    },
    "AMPLIFY_function_LevelUpFitnessChallengeNotificationsLambda_s3Key": {
      "usedBy": [
        {
          "category": "function",
          "resourceName": "LevelUpFitnessChallengeNotificationsLambda"
        }
      ]
    },
    "AMPLIFY_function_LevelUpFitnessCustomProgramRequestLambda_deploymentBucketName": {
      "usedBy": [
        {
          "category": "function",
          "resourceName": "LevelUpFitnessCustomProgramRequestLambda"
        }
      ]
    },
    "AMPLIFY_function_LevelUpFitnessCustomProgramRequestLambda_s3Key": {
      "usedBy": [
        {
          "category": "function",
          "resourceName": "LevelUpFitnessCustomProgramRequestLambda"
        }
      ]
    },
    "AMPLIFY_function_LevelUpFitnessDynamoAccessLambda_deploymentBucketName": {
      "usedBy": [
        {
          "category": "function",
          "resourceName": "LevelUpFitnessDynamoAccessLambda"
        }
      ]
    },
    "AMPLIFY_function_LevelUpFitnessDynamoAccessLambda_s3Key": {
      "usedBy": [
        {
          "category": "function",
          "resourceName": "LevelUpFitnessDynamoAccessLambda"
        }
      ]
    },
    "AMPLIFY_function_LevelUpFitnessS3AccessLambda_deploymentBucketName": {
      "usedBy": [
        {
          "category": "function",
          "resourceName": "LevelUpFitnessS3AccessLambda"
        }
      ]
    },
    "AMPLIFY_function_LevelUpFitnessS3AccessLambda_s3Key": {
      "usedBy": [
        {
          "category": "function",
          "resourceName": "LevelUpFitnessS3AccessLambda"
        }
      ]
    },
    "AMPLIFY_notifications_Pinpoint_Id": {
      "usedBy": [
        {
          "category": "notifications",
          "resourceName": "Pinpoint"
        }
      ]
    },
    "AMPLIFY_notifications_Pinpoint_Name": {
      "usedBy": [
        {
          "category": "notifications",
          "resourceName": "Pinpoint"
        }
      ]
    },
    "AMPLIFY_notifications_Pinpoint_Region": {
      "usedBy": [
        {
          "category": "notifications",
          "resourceName": "Pinpoint"
        }
      ]
    }
  },
  "storage": {
    "LevelUpFitnessBadgesDB": {
      "providerPlugin": "awscloudformation",
      "service": "DynamoDB"
    },
    "LevelUpFitnessChallengeTemplatesDB": {
      "providerPlugin": "awscloudformation",
      "service": "DynamoDB"
    },
    "LevelUpFitnessCustomProgramRequestDB": {
      "providerPlugin": "awscloudformation",
      "service": "DynamoDB"
    },
    "LevelUpFitnessExercisesDB": {
      "providerPlugin": "awscloudformation",
      "service": "DynamoDB"
    },
    "LevelUpFitnessStorage": {
      "dependsOn": [],
      "providerPlugin": "awscloudformation",
      "service": "S3"
    },
    "LevelUpFitnessUserBadgeInfoDB": {
      "providerPlugin": "awscloudformation",
      "service": "DynamoDB"
    },
    "LevelUpFitnessUserChallengesDB": {
      "providerPlugin": "awscloudformation",
      "service": "DynamoDB"
    },
    "LevelUpFitnessUserProgramsDB": {
      "providerPlugin": "awscloudformation",
      "service": "DynamoDB"
    },
    "LevelUpFitnessUserXPInfo": {
      "providerPlugin": "awscloudformation",
      "service": "DynamoDB"
    }
  }
}