{
  "version": 1,
  "paths": {
    "/addUserProgram": {
      "name": "/addUserProgram",
      "lambdaFunction": "LevelUpFitnessDynamoAccessLambda",
      "permissions": {
        "setting": "private",
        "auth": [
          "create",
          "update"
        ]
      }
    },
    "/getUserProgramInfo": {
      "name": "/getUserProgramInfo",
      "lambdaFunction": "LevelUpFitnessDynamoAccessLambda",
      "permissions": {
        "setting": "private",
        "auth": [
          "read"
        ]
      }
    },
    "/getBadges": {
      "name": "/getBadges",
      "lambdaFunction": "LevelUpFitnessDynamoAccessLambda",
      "permissions": {
        "setting": "private",
        "auth": [
          "read"
        ]
      }
    },
    "/modifyUserBadgeInfo": {
      "name": "/modifyUserBadgeInfo",
      "lambdaFunction": "LevelUpFitnessDynamoAccessLambda",
      "permissions": {
        "setting": "private",
        "auth": [
          "create",
          "update"
        ]
      }
    },
    "/getUserBadgeInfo": {
      "name": "/getUserBadgeInfo",
      "lambdaFunction": "LevelUpFitnessDynamoAccessLambda",
      "permissions": {
        "setting": "private",
        "auth": [
          "read"
        ]
      }
    },
    "/getExercises": {
      "name": "/getExercises",
      "lambdaFunction": "LevelUpFitnessDynamoAccessLambda",
      "permissions": {
        "setting": "private",
        "auth": [
          "read"
        ]
      }
    },
    "/getUserXP": {
      "name": "/getUserXP",
      "lambdaFunction": "LevelUpFitnessDynamoAccessLambda",
      "permissions": {
        "setting": "private",
        "auth": [
          "read"
        ]
      }
    },
    "/leaveProgram": {
      "name": "/leaveProgram",
      "lambdaFunction": "LevelUpFitnessDynamoAccessLambda",
      "permissions": {
        "setting": "private",
        "auth": [
          "delete"
        ]
      }
    },
    "/updateUserXP": {
      "name": "/updateUserXP",
      "lambdaFunction": "LevelUpFitnessDynamoAccessLambda",
      "permissions": {
        "setting": "private",
        "auth": [
          "create",
          "update"
        ]
      }
    },
    "/getChallengeTemplates": {
      "name": "/getChallengeTemplates",
      "lambdaFunction": "LevelUpFitnessDynamoAccessLambda",
      "permissions": {
        "setting": "private",
        "auth": [
          "read"
        ]
      }
    },
    "/getActiveUserChallenges": {
      "name": "/getActiveUserChallenges",
      "lambdaFunction": "LevelUpFitnessDynamoAccessLambda",
      "permissions": {
        "setting": "private",
        "auth": [
          "read"
        ]
      }
    },
    "/updateChallenge": {
      "name": "/updateChallenge",
      "lambdaFunction": "LevelUpFitnessDynamoAccessLambda",
      "permissions": {
        "setting": "private",
        "auth": [
          "create",
          "update"
        ]
      }
    },
    "/challengesCompleted": {
      "name": "/challengesCompleted",
      "lambdaFunction": "LevelUpFitnessDynamoAccessLambda",
      "permissions": {
        "setting": "private",
        "auth": [
          "delete"
        ]
      }
    },
    "/addWeightEntry": {
      "name": "/addWeightEntry",
      "lambdaFunction": "LevelUpFitnessDynamoAccessLambda",
      "permissions": {
        "setting": "private",
        "auth": [
          "create",
          "update"
        ]
      }
    },
    "/getUserWeightTrend": {
      "name": "/getUserWeightTrend",
      "lambdaFunction": "LevelUpFitnessDynamoAccessLambda",
      "permissions": {
        "setting": "private",
        "auth": [
          "read"
        ]
      }
    }
  }
}